shadowselenium/__init__.py
shadowselenium/jstrace.py
shadowselenium/shadowselenium.py
shadowselenium-1.0.0.dist-info/WHEEL
shadowselenium-1.0.0.dist-info/METADATA
shadowselenium-1.0.0.dist-info/RECORD
